{"cameraMode":{"drawMode":0,"name":"Shaded","section":"Shading Mode"},"sceneLighting":true,"audioPlay":false,"sceneViewState":{"m_AlwaysRefresh":false,"showFog":true,"showSkybox":true,"showFlares":true,"showImageEffects":true,"showParticleSystems":true,"showVisualEffectGraphs":true,"m_FxEnabled":true},"in2DMode":false,"pivot":{"x":-11.23063850402832,"y":6.032084941864014,"z":-0.054186560213565829},"rotation":{"x":0.12261232733726502,"y":0.8773725628852844,"z":-0.32485637068748476,"w":0.33114784955978396},"size":5.551078796386719,"orthographic":false}